[
  { "rooms": "1", "square": "33.1", "floor": "1", "count": "3630500" },
  { "rooms": "2", "square": "24.5", "floor": "14", "count": "4250000" },
  { "rooms": "3", "square": "105.7", "floor": "7", "count": "7849120" },
  { "rooms": "2", "square": "74.2", "floor": "8", "count": "6830700" },
  { "rooms": "1", "square": "55.6", "floor": "2", "count": "9250006" },
  { "rooms": "1", "square": "92.8", "floor": "12", "count": "13840522" },
  { "rooms": "3", "square": "101.9", "floor": "1", "count": "11430500" },
  { "rooms": "1", "square": "82.6", "floor": "9", "count": "2604700" },
  { "rooms": "3", "square": "98.2", "floor": "15", "count": "12842140" },
  { "rooms": "3", "square": "81.4", "floor": "8", "count": "3630500" },
  { "rooms": "1", "square": "45.2", "floor": "7", "count": "8250000" },
  { "rooms": "3", "square": "51.2", "floor": "11", "count": "10849120" },
  { "rooms": "2", "square": "26.8", "floor": "16", "count": "4630700" },
  { "rooms": "1", "square": "25.4", "floor": "2", "count": "7250006" },
  { "rooms": "2", "square": "77.1", "floor": "3", "count": "10845522" },
  { "rooms": "3", "square": "51.4", "floor": "14", "count": "9430500" },
  { "rooms": "2", "square": "41.5", "floor": "2", "count": "5300400" },
  { "rooms": "2", "square": "97.4", "floor": "9", "count": "8442140" },
  { "rooms": "1", "square": "51.4", "floor": "1", "count": "7308620" },
  { "rooms": "3", "square": "77.9", "floor": "13", "count": "8645124" },
  { "rooms": "1", "square": "33.1", "floor": "1", "count": "3630500" },
  { "rooms": "2", "square": "24.5", "floor": "14", "count": "4250000" },
  { "rooms": "3", "square": "105.7", "floor": "7", "count": "7849120" },
  { "rooms": "2", "square": "74.2", "floor": "8", "count": "6830700" },
  { "rooms": "1", "square": "55.6", "floor": "2", "count": "9250006" },
  { "rooms": "1", "square": "92.8", "floor": "12", "count": "13840522" },
  { "rooms": "3", "square": "101.9", "floor": "1", "count": "11430500" },
  { "rooms": "1", "square": "82.6", "floor": "9", "count": "2604700" },
  { "rooms": "3", "square": "98.2", "floor": "15", "count": "12842140" },
  { "rooms": "3", "square": "81.4", "floor": "8", "count": "3630500" },
  { "rooms": "1", "square": "45.2", "floor": "7", "count": "8250000" },
  { "rooms": "3", "square": "51.2", "floor": "11", "count": "10849120" },
  { "rooms": "2", "square": "26.8", "floor": "16", "count": "4630700" },
  { "rooms": "1", "square": "25.4", "floor": "2", "count": "7250006" },
  { "rooms": "2", "square": "77.1", "floor": "3", "count": "10845522" },
  { "rooms": "3", "square": "51.4", "floor": "14", "count": "9430500" },
  { "rooms": "2", "square": "41.5", "floor": "2", "count": "5300400" },
  { "rooms": "2", "square": "97.4", "floor": "9", "count": "8442140" },
  { "rooms": "1", "square": "51.4", "floor": "1", "count": "7308620" },
  { "rooms": "3", "square": "77.9", "floor": "13", "count": "8645124" },
  { "rooms": "1", "square": "33.1", "floor": "1", "count": "3630500" },
  { "rooms": "2", "square": "24.5", "floor": "14", "count": "4250000" },
  { "rooms": "3", "square": "105.7", "floor": "7", "count": "7849120" },
  { "rooms": "2", "square": "74.2", "floor": "8", "count": "6830700" },
  { "rooms": "1", "square": "55.6", "floor": "2", "count": "9250006" },
  { "rooms": "1", "square": "92.8", "floor": "12", "count": "13840522" },
  { "rooms": "3", "square": "101.9", "floor": "1", "count": "11430500" },
  { "rooms": "1", "square": "82.6", "floor": "9", "count": "2604700" },
  { "rooms": "3", "square": "98.2", "floor": "15", "count": "12842140" },
  { "rooms": "3", "square": "81.4", "floor": "8", "count": "3630500" },
  { "rooms": "1", "square": "45.2", "floor": "7", "count": "8250000" },
  { "rooms": "3", "square": "51.2", "floor": "11", "count": "10849120" },
  { "rooms": "2", "square": "26.8", "floor": "16", "count": "4630700" },
  { "rooms": "1", "square": "25.4", "floor": "2", "count": "7250006" },
  { "rooms": "2", "square": "77.1", "floor": "3", "count": "10845522" },
  { "rooms": "3", "square": "51.4", "floor": "14", "count": "9430500" },
  { "rooms": "2", "square": "41.5", "floor": "2", "count": "5300400" },
  { "rooms": "2", "square": "97.4", "floor": "9", "count": "8442140" },
  { "rooms": "1", "square": "51.4", "floor": "1", "count": "7308620" },
  { "rooms": "3", "square": "77.9", "floor": "13", "count": "8645124" },
  { "rooms": "1", "square": "33.1", "floor": "1", "count": "3630500" },
  { "rooms": "2", "square": "24.5", "floor": "14", "count": "4250000" },
  { "rooms": "3", "square": "105.7", "floor": "7", "count": "7849120" },
  { "rooms": "2", "square": "74.2", "floor": "8", "count": "6830700" },
  { "rooms": "1", "square": "55.6", "floor": "2", "count": "9250006" },
  { "rooms": "1", "square": "92.8", "floor": "12", "count": "13840522" },
  { "rooms": "3", "square": "101.9", "floor": "1", "count": "11430500" },
  { "rooms": "1", "square": "82.6", "floor": "9", "count": "2604700" },
  { "rooms": "3", "square": "98.2", "floor": "15", "count": "12842140" },
  { "rooms": "3", "square": "81.4", "floor": "8", "count": "3630500" },
  { "rooms": "1", "square": "45.2", "floor": "7", "count": "8250000" },
  { "rooms": "3", "square": "51.2", "floor": "11", "count": "10849120" },
  { "rooms": "2", "square": "26.8", "floor": "16", "count": "4630700" },
  { "rooms": "1", "square": "25.4", "floor": "2", "count": "7250006" },
  { "rooms": "2", "square": "77.1", "floor": "3", "count": "10845522" },
  { "rooms": "3", "square": "51.4", "floor": "14", "count": "9430500" },
  { "rooms": "2", "square": "41.5", "floor": "2", "count": "5300400" },
  { "rooms": "2", "square": "97.4", "floor": "9", "count": "8442140" },
  { "rooms": "1", "square": "51.4", "floor": "1", "count": "7308620" },
  { "rooms": "3", "square": "77.9", "floor": "13", "count": "8645124" },
  { "rooms": "1", "square": "33.1", "floor": "1", "count": "3630500" },
  { "rooms": "2", "square": "24.5", "floor": "14", "count": "4250000" },
  { "rooms": "3", "square": "105.7", "floor": "7", "count": "7849120" },
  { "rooms": "2", "square": "74.2", "floor": "8", "count": "6830700" },
  { "rooms": "1", "square": "55.6", "floor": "2", "count": "9250006" },
  { "rooms": "1", "square": "92.8", "floor": "12", "count": "13840522" },
  { "rooms": "3", "square": "101.9", "floor": "1", "count": "11430500" },
  { "rooms": "1", "square": "82.6", "floor": "9", "count": "2604700" },
  { "rooms": "3", "square": "98.2", "floor": "15", "count": "12842140" },
  { "rooms": "3", "square": "81.4", "floor": "8", "count": "3630500" },
  { "rooms": "1", "square": "45.2", "floor": "7", "count": "8250000" },
  { "rooms": "3", "square": "51.2", "floor": "11", "count": "10849120" },
  { "rooms": "2", "square": "26.8", "floor": "16", "count": "4630700" },
  { "rooms": "1", "square": "25.4", "floor": "2", "count": "7250006" },
  { "rooms": "2", "square": "77.1", "floor": "3", "count": "10845522" },
  { "rooms": "3", "square": "51.4", "floor": "14", "count": "9430500" },
  { "rooms": "2", "square": "41.5", "floor": "2", "count": "5300400" },
  { "rooms": "2", "square": "97.4", "floor": "9", "count": "8442140" },
  { "rooms": "1", "square": "51.4", "floor": "1", "count": "7308620" },
  { "rooms": "3", "square": "77.9", "floor": "13", "count": "8645124" }
]
